{"_type":"export","__export_format":4,"__export_date":"2019-06-17T15:54:35.073Z","__export_source":"insomnia.desktop.app:v6.5.3","resources":[{"_id":"req_c6629da12ca14026ac8a8f0450cb5600","authentication":{},"body":{},"created":1560656662522,"description":"","headers":[],"isPrivate":false,"metaSortKey":-1560656662522,"method":"GET","modified":1560708892371,"name":"Get specific task","parameters":[],"parentId":"wrk_fbbdff1c56894c189a057e88bc59a861","settingDisableRenderRequestBody":false,"settingEncodeUrl":true,"settingRebuildPath":true,"settingSendCookies":true,"settingStoreCookies":true,"url":"http://130.211.234.175/todo/public/api/task/53","_type":"request"},{"_id":"wrk_fbbdff1c56894c189a057e88bc59a861","created":1560654657185,"description":"","modified":1560654657185,"name":"Google Tech Talk","parentId":null,"_type":"workspace"},{"_id":"req_506756b29e4c4673b253595b9d097a74","authentication":{},"body":{"mimeType":"multipart/form-data","params":[{"id":"pair_b7ff4dc767fd43e7b92e4b66e3f2e70e","name":"_method","value":"put"},{"id":"pair_fde3a08e6c6a4531a858f4b06e46b60d","name":"task_id","value":"53"},{"id":"pair_819f13c5f6e94f7e92a3ee28a5dd8d07","name":"name","value":"Test"},{"id":"pair_bb68ce428bad41969ace8fb1f3fbfd47","name":"description","value":"Test Description"}]},"created":1560656618279,"description":"","headers":[{"id":"pair_1de7063527574ed198bf2727cc77202d","name":"Content-Type","value":"multipart/form-data"}],"isPrivate":false,"metaSortKey":-1560656618279,"method":"POST","modified":1560720902783,"name":"Update existing task","parameters":[],"parentId":"wrk_fbbdff1c56894c189a057e88bc59a861","settingDisableRenderRequestBody":false,"settingEncodeUrl":true,"settingRebuildPath":true,"settingSendCookies":true,"settingStoreCookies":true,"url":"http://130.211.234.175/todo/public/api/task","_type":"request"},{"_id":"req_fde235d839bf4a508d97adf9c42c65bb","authentication":{},"body":{"mimeType":"multipart/form-data","params":[{"id":"pair_49f45a9cf8e440c8970f42edd8d5271f","name":"name","value":"Test Task"},{"id":"pair_53fd64d203a64bc8add249f595a3f128","name":"description","value":"Description text"}]},"created":1560656602095,"description":"","headers":[{"id":"pair_98232befa0594efe9d30acde3b56931d","name":"Content-Type","value":"multipart/form-data"}],"isPrivate":false,"metaSortKey":-1560656602095,"method":"POST","modified":1560659034619,"name":"Create new task","parameters":[],"parentId":"wrk_fbbdff1c56894c189a057e88bc59a861","settingDisableRenderRequestBody":false,"settingEncodeUrl":true,"settingRebuildPath":true,"settingSendCookies":true,"settingStoreCookies":true,"url":"http://130.211.234.175/todo/public/api/task","_type":"request"},{"_id":"req_42ab0c4e8e76429492834e0cbce710f0","authentication":{},"body":{},"created":1560655589045,"description":"","headers":[],"isPrivate":false,"metaSortKey":-1560655589045,"method":"DELETE","modified":1560697379516,"name":"Delete a Task","parameters":[],"parentId":"wrk_fbbdff1c56894c189a057e88bc59a861","settingDisableRenderRequestBody":false,"settingEncodeUrl":true,"settingRebuildPath":true,"settingSendCookies":true,"settingStoreCookies":true,"url":"http://130.211.234.175/todo/public/api/task/53","_type":"request"},{"_id":"req_e93e2ee2458d402e932b5cba98dbdf6e","authentication":{},"body":{},"created":1560654676415,"description":"","headers":[],"isPrivate":false,"metaSortKey":-1560654676415,"method":"GET","modified":1560655009475,"name":"Get Tasks","parameters":[],"parentId":"wrk_fbbdff1c56894c189a057e88bc59a861","settingDisableRenderRequestBody":false,"settingEncodeUrl":true,"settingRebuildPath":true,"settingSendCookies":true,"settingStoreCookies":true,"url":"http://130.211.234.175/todo/public/api/tasks","_type":"request"},{"_id":"env_9be5eb759d19bd02e7977fa1561f0e7d5757fdf1","color":null,"created":1560654657687,"data":{},"isPrivate":false,"metaSortKey":1560654657687,"modified":1560654657687,"name":"Base Environment","parentId":"wrk_fbbdff1c56894c189a057e88bc59a861","_type":"environment"},{"_id":"jar_9be5eb759d19bd02e7977fa1561f0e7d5757fdf1","cookies":[],"created":1560654657690,"modified":1560654657690,"name":"Default Jar","parentId":"wrk_fbbdff1c56894c189a057e88bc59a861","_type":"cookie_jar"}]}